rewards/VERSION
rewards/__init__.py
rewards/agent.py
rewards/assets/CarRace/car.png
rewards/assets/CarRace/track_test_3.png
rewards/assets/CarRace/track_test_4.png
rewards/assets/CarRace/track_test_5.jpg
rewards/assets/CarRace/track_test_5.png
rewards/assets/CarRace/track_test_6.png
rewards/assets/CarRace/track_test_7.png
rewards/envs/car.py
rewards/models.py
rewards/trainer.py
rewards/workflow.py
rewards-1.0.2.dist-info/METADATA
rewards-1.0.2.dist-info/WHEEL
rewards-1.0.2.dist-info/RECORD
