Metadata-Version: 2.1
Name: rewards
Version: 1.0.2
Summary: A low code sdk for crearing custom environments and deep RL agents.
License: MIT
Author: Anindyadeep
Author-email: 2005641@kiit.ac.in
Requires-Python: >=3.10,<4.0
Classifier: License :: OSI Approved :: MIT License
Classifier: Programming Language :: Python :: 3
Classifier: Programming Language :: Python :: 3.10
Classifier: Programming Language :: Python :: 3.11
Requires-Dist: PyQt5 (>=5.15.9,<6.0.0)
Requires-Dist: lightning (>=2.0.1,<3.0.0)
Requires-Dist: matplotlib (>=3.7.1,<4.0.0)
Requires-Dist: numpy (>=1.24.2,<2.0.0)
Requires-Dist: pandas (>=1.5.3,<2.0.0)
Requires-Dist: pygame (>=2.3.0,<3.0.0)
Requires-Dist: pyqtgraph (>=0.13.2,<0.14.0)
Requires-Dist: scikit-learn (>=1.2.2,<2.0.0)
Requires-Dist: torch (>=2.0.0,<3.0.0)
Requires-Dist: wandb (>=0.14.0,<0.15.0)
